{
  "rootObjects": [
    {
      "id": "__00001__",
      "name": null
    }
  ],
  "objects": {
    "__00001__": {
      "subscriptions": "__00002__",
      "unqfy": "__00003__",
      "listeners": "__00004__"
    },
    "__00002__": {
      "0": "__00005__"
    },
    "__00003__": {
      "baseURL": "http://localhost:8080/api"
    },
    "__00004__": {},
    "__00005__": {
      "artist": 25,
      "users": "__00006__"
    },
    "__00006__": {
      "0": "liza.chambi@gmail.com"
    }
  },
  "types": {
    "__00001__": "Notifier",
    "__00002__": "Array",
    "__00003__": "ServiceUNQfy",
    "__00004__": "Array",
    "__00005__": "Suscription",
    "__00006__": "Array"
  }
}